get_the_nini/__init__.py
get_the_nini/main.py
get_the_nini-0.1.4.dist-info/METADATA
get_the_nini-0.1.4.dist-info/WHEEL
get_the_nini-0.1.4.dist-info/entry_points.txt
get_the_nini-0.1.4.dist-info/RECORD
