Metadata-Version: 2.3
Name: get-the-nini
Version: 0.1.4
Summary: Ninisite Scraper: Fetches all pages of a Ninisite discussion and formats in org-mode, Markdown, or JSON
Author: Feraidoon
Author-email: feraidoonmehri@gmail.com
Requires-Python: >=3.8,<4.0
Classifier: Programming Language :: Python :: 3
Classifier: Programming Language :: Python :: 3.8
Classifier: Programming Language :: Python :: 3.9
Classifier: Programming Language :: Python :: 3.10
Classifier: Programming Language :: Python :: 3.11
Classifier: Programming Language :: Python :: 3.12
Classifier: Programming Language :: Python :: 3.13
Requires-Dist: beautifulsoup4 (>=4.9.0,<5.0.0)
Requires-Dist: pypandoc (>=1.6.0,<2.0.0)
Requires-Dist: pytz (>=2021.1,<2022.0)
Requires-Dist: requests (>=2.25.0,<3.0.0)
Requires-Dist: tqdm (>=4.60.0,<5.0.0)
